LiRPC/__init__.py
LiRPC/core.py
LiRPC/test.py
LiRPC-0.1.2.dist-info/LICENSE
LiRPC-0.1.2.dist-info/METADATA
LiRPC-0.1.2.dist-info/WHEEL
LiRPC-0.1.2.dist-info/top_level.txt
LiRPC-0.1.2.dist-info/RECORD
