Metadata-Version: 2.1
Name: LiRPC
Version: 0.1.2
Summary: liziyi0914's RPC module
Home-page: https://github.com/liziyi0914/LiRPC
Author: liziyi0914
Author-email: liziyi0914@gmail.com
License: GPL License
Platform: all
